sizebytes_tools/__init__.py
sizebytes_tools/functions/__init__.py
sizebytes_tools/functions/sizebytes.py
sizebytes_tools-0.0.3.dist-info/LICENSE
sizebytes_tools-0.0.3.dist-info/METADATA
sizebytes_tools-0.0.3.dist-info/WHEEL
sizebytes_tools-0.0.3.dist-info/top_level.txt
sizebytes_tools-0.0.3.dist-info/RECORD
