Metadata-Version: 2.1
Name: sizebytes-tools
Version: 0.0.3
Summary: sizebytes_tools
Home-page: https://github.com/jonaqp/sizebytes_tools/
Author: Jonathan Quiza
Author-email: jony327@gmail.com
License: UNKNOWN
Download-URL: https://github.com/jonaqp/sizebytes_tools/archive/main.zip
Keywords: sizebytes,MB,GB
Platform: UNKNOWN
Classifier: Development Status :: 5 - Production/Stable
Classifier: Intended Audience :: Developers
Classifier: Intended Audience :: Science/Research
Classifier: Topic :: Scientific/Engineering :: Artificial Intelligence
Classifier: License :: OSI Approved :: Apache Software License
Classifier: Programming Language :: Python :: 3.8
Classifier: Programming Language :: Python :: 3.7
